speedpy/__init__.py
speedpy/speedpy.py
speedpy-1.0.1.dist-info/LICENSE
speedpy-1.0.1.dist-info/METADATA
speedpy-1.0.1.dist-info/WHEEL
speedpy-1.0.1.dist-info/top_level.txt
speedpy-1.0.1.dist-info/RECORD
