Metadata-Version: 2.1
Name: speedpy
Version: 1.0.1
Summary: Python function speed analysis tool
Home-page: https://github.com/ryanxjhan/speedpy
Author: Ryan Han
Author-email: realryanhan@gmail.com
License: MIT
Platform: UNKNOWN
Classifier: License :: OSI Approved :: MIT License
Classifier: Programming Language :: Python :: 3
Classifier: Programming Language :: Python :: 3.7
Requires-Dist: cProfile
Requires-Dist: pstats
Requires-Dist: asyncio
